polygenerator.py
polygenerator-0.2.0.dist-info/LICENSE
polygenerator-0.2.0.dist-info/WHEEL
polygenerator-0.2.0.dist-info/METADATA
polygenerator-0.2.0.dist-info/RECORD
