Metadata-Version: 2.1
Name: polygenerator
Version: 0.2.0
Summary: Generates random simple polygons.
Home-page: https://github.com/bast/polygenerator
Author: Radovan Bast
Author-email: radovan.bast@uit.no
Classifier: License :: OSI Approved :: MIT License
